fastsam/__init__.py
fastsam/decoder.py
fastsam/model.py
fastsam/predict.py
fastsam/prompt.py
fastsam/utils.py
segment_anything_fast-0.1.2.dist-info/LICENSE
segment_anything_fast-0.1.2.dist-info/METADATA
segment_anything_fast-0.1.2.dist-info/WHEEL
segment_anything_fast-0.1.2.dist-info/dependency_links.txt
segment_anything_fast-0.1.2.dist-info/top_level.txt
segment_anything_fast-0.1.2.dist-info/RECORD
