Metadata-Version: 2.1
Name: segment-anything-fast
Version: 0.1.2
Summary: Fast Segment Anything
Home-page: https://github.com/opengeos/FastSAM
Author: Qiusheng Wu
Author-email: giswqs@gmail.com
License: Apache Software License
Keywords: segment-anything
Classifier: Intended Audience :: Developers
Classifier: License :: OSI Approved :: Apache Software License
Classifier: Natural Language :: English
Classifier: Programming Language :: Python :: 3
Classifier: Programming Language :: Python :: 3.8
Classifier: Programming Language :: Python :: 3.9
Classifier: Programming Language :: Python :: 3.10
Classifier: Programming Language :: Python :: 3.11
Requires-Python: >=3.8
License-File: LICENSE
Requires-Dist: matplotlib >=3.2.2
Requires-Dist: opencv-python >=4.6.0
Requires-Dist: Pillow >=7.1.2
Requires-Dist: PyYAML >=5.3.1
Requires-Dist: requests >=2.23.0
Requires-Dist: scipy >=1.4.1
Requires-Dist: torch >=1.7.0
Requires-Dist: torchvision >=0.8.1
Requires-Dist: tqdm >=4.64.0
Requires-Dist: pandas >=1.1.4
Requires-Dist: seaborn >=0.11.0
Requires-Dist: gradio <=3.35.2
Requires-Dist: ultralytics <=8.0.122
Requires-Dist: openai-clip
